keyring_insecure_backend/ConfFileModel.py
keyring_insecure_backend/ConfLoggingModel.py
keyring_insecure_backend/ConfRichLoggingModel.py
keyring_insecure_backend/InsecureKeyringBackend.py
keyring_insecure_backend/__init__.py
keyring_insecure_backend-0.0.0.dist-info/METADATA
keyring_insecure_backend-0.0.0.dist-info/WHEEL
keyring_insecure_backend-0.0.0.dist-info/entry_points.txt
keyring_insecure_backend-0.0.0.dist-info/RECORD
