Metadata-Version: 2.4
Name: keyring-insecure-backend
Version: 0.0.0
Summary: An insecure Keyring backend that stores secrets in plain text.
Author-email: Stefan Schablowski <stefan.schablowski@desmodyne.com>
License: MIT
Classifier: Development Status :: 3 - Alpha
Classifier: Environment :: Console
Classifier: Intended Audience :: Developers
Classifier: License :: OSI Approved :: MIT License
Classifier: Natural Language :: English
Classifier: Operating System :: OS Independent
Classifier: Programming Language :: Python :: 3
Classifier: Topic :: Security
Classifier: Typing :: Typed
Requires-Python: >=3.10
Requires-Dist: keyring>=25.6.0
Requires-Dist: platformdirs>=4.3.6
Requires-Dist: pydantic>=2.10.6
Requires-Dist: pyyaml>=6.0.2
Requires-Dist: rich>=13.9.4
